[{"type":"Double","value":25.0,"valueInfo":{},"id":"b3bc8aec-4564-11f1-8f49-1a64415e5b3c","name":"valorCotacao","processDefinitionKey":"cotacao_delivery","processDefinitionId":"cotacao_delivery:1:09413804-455d-11f1-8f49-1a64415e5b3c","processInstanceId":"b3b8ba51-4564-11f1-8f49-1a64415e5b3c","executionId":"b3b8ba51-4564-11f1-8f49-1a64415e5b3c","activityInstanceId":"b3b8ba51-4564-11f1-8f49-1a64415e5b3c","caseDefinitionKey":null,"caseDefinitionId":null,"caseInstanceId":null,"caseExecutionId":null,"taskId":null,"errorMessage":null,"tenantId":null,"state":"CREATED","createTime":"2026-05-01T13:50:23.972+0000","removalTime":"2026-10-28T13:50:23.974+0000","rootProcessInstanceId":"b3b8ba51-4564-11f1-8f49-1a64415e5b3c"}]